asyncbg/__init__.py
asyncbg/version.py
asyncbg-0.12.0.dist-info/LICENSE
asyncbg-0.12.0.dist-info/METADATA
asyncbg-0.12.0.dist-info/WHEEL
asyncbg-0.12.0.dist-info/top_level.txt
asyncbg-0.12.0.dist-info/RECORD
