Metadata-Version: 2.1
Name: asyncbg
Version: 0.12.0
Summary: Asyncio background tasks.
Home-page: https://github.com/eerimoq/asyncbg
Author: Erik Moqvist
Author-email: erik.moqvist@gmail.com
License: MIT
Keywords: asyncio
Classifier: License :: OSI Approved :: MIT License
Classifier: Programming Language :: Python :: 3
License-File: LICENSE
